{
  "version": 2,
  "projects": {
    "gateway-web": {
      "root": "apps/gateway/web",
      "sourceRoot": "apps/gateway/web/src",
      "projectType": "application",
      "targets": {
        "build": {
          "executor": "@nrwl/web:build",
          "outputs": ["{options.outputPath}"],
          "options": {
            "outputPath": "dist/apps/gateway/web",
            "index": "apps/gateway/web/src/index.html",
            "main": "apps/gateway/web/src/main.tsx",
            "polyfills": "apps/gateway/web/src/polyfills.ts",
            "tsConfig": "apps/gateway/web/tsconfig.app.json",
            "assets": [
              "apps/gateway/web/src/favicon.ico",
              "apps/gateway/web/src/assets"
            ],
            "styles": ["apps/gateway/web/src/styles.scss"],
            "scripts": [],
            "webpackConfig": "@nrwl/react/plugins/webpack"
          },
          "configurations": {
            "production": {
              "fileReplacements": [
                {
                  "replace": "apps/gateway/web/src/environments/environment.ts",
                  "with": "apps/gateway/web/src/environments/environment.prod.ts"
                }
              ],
              "optimization": true,
              "outputHashing": "all",
              "sourceMap": false,
              "extractCss": true,
              "namedChunks": false,
              "extractLicenses": true,
              "vendorChunk": false,
              "budgets": [
                {
                  "type": "initial",
                  "maximumWarning": "500kb",
                  "maximumError": "1mb"
                }
              ]
            }
          }
        },
        "serve": {
          "executor": "@nrwl/web:dev-server",
          "options": {
            "buildTarget": "gateway-web:build",
            "hmr": true
          },
          "configurations": {
            "production": {
              "buildTarget": "gateway-web:build:production",
              "hmr": false
            }
          }
        },
        "lint": {
          "executor": "@nrwl/linter:eslint",
          "outputs": ["{options.outputFile}"],
          "options": {
            "lintFilePatterns": ["apps/gateway/web/**/*.{ts,tsx,js,jsx}"]
          }
        },
        "test": {
          "executor": "@nrwl/jest:jest",
          "outputs": ["coverage/apps/gateway/web"],
          "options": {
            "jestConfig": "apps/gateway/web/jest.config.js",
            "passWithNoTests": true
          }
        }
      }
    },
    "gateway/web-e2e": {
      "root": "apps/gateway/web-e2e",
      "sourceRoot": "apps/gateway/web-e2e/src",
      "projectType": "application",
      "targets": {
        "e2e": {
          "executor": "@nrwl/cypress:cypress",
          "options": {
            "cypressConfig": "apps/gateway/web-e2e/cypress.json",
            "devServerTarget": "gateway-web:serve",
            "tsConfig": "apps/gateway/web-e2e/tsconfig.json"
          },
          "configurations": {
            "production": {
              "devServerTarget": "gateway-web:serve:production"
            }
          }
        },
        "lint": {
          "executor": "@nrwl/linter:eslint",
          "outputs": ["{options.outputFile}"],
          "options": {
            "lintFilePatterns": ["apps/gateway/web-e2e/**/*.{js,ts}"]
          }
        }
      }
    }
  },
  "cli": {
    "defaultCollection": "@nrwl/react"
  },
  "generators": {
    "@nrwl/react": {
      "application": {
        "style": "scss",
        "linter": "eslint",
        "babel": true
      },
      "component": {
        "style": "scss"
      },
      "library": {
        "style": "scss",
        "linter": "eslint"
      }
    }
  },
  "defaultProject": "gateway-web"
}
